My_Toolbox_zhaozl/__init__.py
My_Toolbox_zhaozl/__version__.py
My_Toolbox_zhaozl/core.py
My_Toolbox_zhaozl-1.3.dist-info/LICENSE
My_Toolbox_zhaozl-1.3.dist-info/METADATA
My_Toolbox_zhaozl-1.3.dist-info/WHEEL
My_Toolbox_zhaozl-1.3.dist-info/top_level.txt
My_Toolbox_zhaozl-1.3.dist-info/RECORD
